odoo/addons/nutritional_info_stock_lot/README.rst
odoo/addons/nutritional_info_stock_lot/__init__.py
odoo/addons/nutritional_info_stock_lot/__manifest__.py
odoo/addons/nutritional_info_stock_lot/i18n/es.po
odoo/addons/nutritional_info_stock_lot/i18n/nutritional_info_stock_lot.pot
odoo/addons/nutritional_info_stock_lot/models/__init__.py
odoo/addons/nutritional_info_stock_lot/models/nutritional_value.py
odoo/addons/nutritional_info_stock_lot/models/stock_production_lot.py
odoo/addons/nutritional_info_stock_lot/readme/CONFIGURE.rst
odoo/addons/nutritional_info_stock_lot/readme/CONTRIBUTORS.rst
odoo/addons/nutritional_info_stock_lot/readme/DESCRIPTION.rst
odoo/addons/nutritional_info_stock_lot/readme/USAGE.rst
odoo/addons/nutritional_info_stock_lot/report/report_nutritional_info.xml
odoo/addons/nutritional_info_stock_lot/security/ir.model.access.csv
odoo/addons/nutritional_info_stock_lot/static/description/icon.png
odoo/addons/nutritional_info_stock_lot/static/description/index.html
odoo/addons/nutritional_info_stock_lot/views/stock_menu_views.xml
odoo/addons/nutritional_info_stock_lot/views/stock_production_lot_view.xml
odoo_addon_nutritional_info_stock_lot-15.0.1.1.0.dist-info/METADATA
odoo_addon_nutritional_info_stock_lot-15.0.1.1.0.dist-info/WHEEL
odoo_addon_nutritional_info_stock_lot-15.0.1.1.0.dist-info/top_level.txt
odoo_addon_nutritional_info_stock_lot-15.0.1.1.0.dist-info/RECORD
